ipdd/__init__.py
ipdd/downloader.py
ipdd-3.0.dist-info/METADATA
ipdd-3.0.dist-info/WHEEL
ipdd-3.0.dist-info/entry_points.txt
ipdd-3.0.dist-info/top_level.txt
ipdd-3.0.dist-info/RECORD
